django_cbtp_email/__init__.py
django_cbtp_email/admin.py
django_cbtp_email/apps.py
django_cbtp_email/errors.py
django_cbtp_email/mail_funcs.py
django_cbtp_email/mailer.py
django_cbtp_email/models.py
django_cbtp_email/urls.py
django_cbtp_email/views.py
django_cbtp_email/templatetags/__init__.py
django_cbtp_email/templatetags/mailing_tags.py
django_cbtp_email-0.1.4.dist-info/DESCRIPTION.rst
django_cbtp_email-0.1.4.dist-info/METADATA
django_cbtp_email-0.1.4.dist-info/RECORD
django_cbtp_email-0.1.4.dist-info/WHEEL
django_cbtp_email-0.1.4.dist-info/metadata.json
django_cbtp_email-0.1.4.dist-info/top_level.txt
