Metadata-Version: 2.0
Name: django-cbtp-email
Version: 0.1.4
Summary: Class-based mailer for Django using templates with inlined CSS.
Home-page: https://github.com/illagrenan/django-cbtp-email
Author: Vašek Dohnal
Author-email: vaclav.dohnal@gmail.com
License: MIT
Requires-Dist: django
Requires-Dist: django-annoying
Requires-Dist: premailer
